<!DOCTYPE settings SYSTEM "settings.dtd">

<settings>
  <dl_settings>

    <dl_settings NAME="Extras">
      <dl_setting var="ahrs_mag_offset" min="-25" step="0.1" max="25" module="subsystems/ahrs"/>
      <dl_setting var="min_bound" min="0" step="1" max="20"   module="guidance/guidance_v"/>
      <dl_setting var="max_bound" min="0" step="1" max="20"   module="guidance/guidance_v"/>
      <dl_setting var="nom_thrust" min="90" step="1" max="130"   module="guidance/guidance_v"/>
    </dl_settings>

   
  </dl_settings>
</settings>
